{
    "parent": "flansvendersgame:item/fc_puncher/default",
    "overrides": [
        {
            "predicate": {
                "custom_model_data": 1
            },
            "model": "flansvendersgame:item/fc_puncher/fc_puncher_birch"
        },
        {
            "predicate": {
                "custom_model_data": 2
            },
            "model": "flansvendersgame:item/fc_puncher/fc_puncher_blackwood"
        },
        {
            "predicate": {
                "custom_model_data": 3
            },
            "model": "flansvendersgame:item/fc_puncher/fc_puncher_dark"
        },
        {
            "predicate": {
                "custom_model_data": 4
            },
            "model": "flansvendersgame:item/fc_puncher/fc_puncher_static"
        }
    ]
}