{
    "canPlaceInMachiningTable": false,
    "canPlaceInModificationTable": false,
    "compatiblityTags": [
        "mecha",
        "groundVehicle",
        "plane"
    ],
    "itemSettings": {
        "maxStackSize": 64,
        "tags": [
            "flansmod:part",
            "flansmod:engine"
        ]
    },
    "modifiers": [],
    "abilities": [],
    "engine": {
        "maxAcceleration": 0.8,
        "maxDeceleration": 0.8,
        "maxSpeed": 0.8,
        "fuelType": "FE",
        "fuelConsumptionRate": 10.0,
        "solidFuelSlots": 0,
        "liquidFuelCapacity": 0,
        "batterySlots": 1,
        "FECapacity": 10000
    },
    "materialTier": 1,
    "materialType": "Electronic"
}